npsearchsequence/README.MD
npsearchsequence/__init__.py
npsearchsequence/requirements.txt
npsearchsequence/thirdparty.json
npsearchsequence-0.10.dist-info/LICENSE.rst
npsearchsequence-0.10.dist-info/METADATA
npsearchsequence-0.10.dist-info/WHEEL
npsearchsequence-0.10.dist-info/top_level.txt
npsearchsequence-0.10.dist-info/RECORD
