Metadata-Version: 2.1
Name: npsearchsequence
Version: 0.10
Summary: Sequence / string search with NumPy
Home-page: https://github.com/hansalemaos/npsearchsequence
Author: Johannes Fischer
Author-email: aulasparticularesdealemaosp@gmail.com
License: MIT
Keywords: sequence,search,string,numpy
Classifier: Development Status :: 4 - Beta
Classifier: Programming Language :: Python :: 3 :: Only
Classifier: Programming Language :: Python :: 3.10
Classifier: Topic :: Software Development :: Libraries :: Python Modules
Classifier: Topic :: Utilities
License-File: LICENSE.rst
Requires-Dist: numpy
